python_easy_facebook_api/__init__.py
python_easy_facebook_api/facebook_service.py
python_easy_facebook_api/fb_api.py
python_easy_facebook_api/photo_post.py
python_easy_facebook_api/text_post.py
python_easy_facebook_api/text_with_photo_post.py
python_easy_facebook_api/types.py
python_easy_facebook_api/video_post.py
python_easy_facebook_api-1.0.1.dist-info/METADATA
python_easy_facebook_api-1.0.1.dist-info/WHEEL
python_easy_facebook_api-1.0.1.dist-info/top_level.txt
python_easy_facebook_api-1.0.1.dist-info/RECORD
