Metadata-Version: 2.1
Name: python-easy-facebook-api
Version: 1.0.1
Summary: Library for content creation automation on Facebook
Home-page: https://github.com/seokkuuu/python_easy_facebook_api
Author: Seokku
Author-email: 
License: MIT
Requires-Dist: requests
